cpu.v
///////////////////////////////////////////////////////////////////////////
// MODULE: CPU for TSC microcomputer: cpu.v
// Author: 
// Description: 

// DEFINITIONS

`define WORD_SIZE 16    // data and address word size

// MODULE DECLARATION
module cpu (
    output readM,                       // read from memory
    output [`WORD_SIZE-1:0] address,    // current address for data
    inout [`WORD_SIZE-1:0] data,        // data being input or output
    input inputReady,                   // indicates that data is ready from the input port
    input reset_n,                      // active-low RESET signal
    input clk,                          // clock signal
  
    // for debuging/testing purpose
    output [`WORD_SIZE-1:0] num_inst,   // number of instruction during execution
    output [`WORD_SIZE-1:0] output_port // this will be used for a "WWD" instruction 
);
// 1. 명령어 페치
    assign readM = 1'b1;
    wire [`WORD_SIZE-1:0] pc_out;
    assign address = pc_out;

    reg [`WORD_SIZE-1:0] instruction;
    always @(*) begin               // inputReady 구간에 data를 래치
        if (inputReady) instruction = data;
    end

    // 2. 필드 분해
    wire [1:0]  rs     = instruction[11:10];
    wire [1:0]  rt     = instruction[9:8];
    wire [1:0]  rd     = instruction[7:6];
    wire [7:0]  imm    = instruction[7:0];
    wire [11:0] target = instruction[11:0];

    // 3. Control Unit
    wire RegWrite, RegDst, ALUSrc, isLHI, isJMP, isWWD;
    wire [2:0] ALUOp;
    ControlUnit CU (
        .instruction(instruction),
        .RegWrite(RegWrite), .RegDst(RegDst), .ALUSrc(ALUSrc),
        .ALUOp(ALUOp), .isLHI(isLHI), .isJMP(isJMP), .isWWD(isWWD)
    );

    // 4. Register File  (RF는 active-high reset이므로 ~reset_n)
    wire [1:0] write_addr = RegDst ? rd : rt;       // RegDst MUX
    wire [`WORD_SIZE-1:0] reg_data1, reg_data2, write_data;
    RF rf (
        .addr1(rs), .addr2(rt), .addr3(write_addr),
        .data3(write_data), .write(RegWrite),
        .clk(clk), .reset(~reset_n),
        .data1(reg_data1), .data2(reg_data2)
    );

    // 5. ALU
    wire [`WORD_SIZE-1:0] sign_ext = {{8{imm[7]}}, imm};        // 부호확장
    wire [`WORD_SIZE-1:0] alu_B = ALUSrc ? sign_ext : reg_data2; // ALUSrc MUX
    wire [`WORD_SIZE-1:0] alu_C; wire alu_Cout;
    ALU alu (
        .A(reg_data1), .B(alu_B), .Cin(1'b0),
        .OP({1'b0, ALUOp}),         // 3비트 ALUOp -> 4비트 OP (ADD=0)
        .Cout(alu_Cout), .C(alu_C)
    );

    // 6. Write-back MUX (LHI vs ALU)
    wire [`WORD_SIZE-1:0] lhi_val = {imm, 8'b0};
    assign write_data = isLHI ? lhi_val : alu_C;

    // 7. PC
    PC pc (
        .clk(clk), .reset_n(reset_n),
        .isJMP(isJMP), .jump_target(target),
        .pc_out(pc_out)
    );
    reg [`WORD_SIZE-1:0] num_inst_r;
    reg [`WORD_SIZE-1:0] output_port_r;

    assign num_inst    = num_inst_r;
    assign output_port = output_port_r;
    // 8. num_inst / output_port
    always @(posedge clk or negedge reset_n) begin
        if (!reset_n) begin
            num_inst_r    <= 16'b0;
            output_port_r <= 16'b0;
        end else begin
            num_inst_r <= num_inst_r + 1;
            if (isWWD) output_port_r <= reg_data1;   // WWD $rs
        end
    end
  
endmodule

`define OPCODE_R    4'd15
`define OPCODE_ADI  4'd4
`define OPCODE_LHI  4'd6
`define OPCODE_JMP  4'd9

`define FUNC_ADD    6'd0
`define FUNC_WWD    6'd28

module PC (
    input                       clk,
    input                       reset_n,       // active-low reset
    input                       isJMP,         // from Control Unit
    input  [11:0]               jump_target,   // instruction[11:0]
    output reg [`WORD_SIZE-1:0] pc_out         // current PC value
);

    always @(posedge clk or negedge reset_n) begin
        if (!reset_n) begin
            // ---- Reset: PC starts from address 0 ----
            pc_out <= 16'b0;
        end
        else begin
            if (isJMP) begin
                // ---- JMP: PC <- {PC[15:12], target[11:0]} ----
                pc_out <= {pc_out[15:12], jump_target};
            end
            else begin
                // ---- Normal: PC <- PC + 1 ----
                pc_out <= pc_out + 1;
            end
        end
    end

endmodule


module ControlUnit (
    input  [`WORD_SIZE-1:0] instruction,  // 16-bit instruction from memory
    
    output reg       RegWrite,
    output reg       RegDst,
    output reg       ALUSrc,
    output reg [2:0] ALUOp,
    output reg       isLHI,
    output reg       isJMP,
    output reg       isWWD
);

    // ---- Extract fields from instruction ----
    wire [3:0] opcode;
    wire [5:0] func;
    
    assign opcode = instruction[15:12];
    assign func   = instruction[5:0];

    always @(*) begin
        // ---- Default values ----
        RegWrite = 1'b0;
        RegDst   = 1'b0;
        ALUSrc   = 1'b0;
        ALUOp    = 3'b000;
        isLHI    = 1'b0;
        isJMP    = 1'b0;
        isWWD    = 1'b0;
        
        case (opcode)
            `OPCODE_R: begin
                case (func)
                    `FUNC_ADD: begin
                        RegWrite = 1'b1;
                        RegDst   = 1'b1;
                        ALUSrc   = 1'b0;
                        ALUOp    = 3'b000;
                    end
                    `FUNC_WWD: begin
                        isWWD    = 1'b1;
                    end
                endcase
            end
            
            `OPCODE_ADI: begin
                RegWrite = 1'b1;
                RegDst   = 1'b0;
                ALUSrc   = 1'b1;
                ALUOp    = 3'b000;
            end
            
            `OPCODE_LHI: begin
                RegWrite = 1'b1;
                RegDst   = 1'b0;
                isLHI    = 1'b1;
            end
            
            `OPCODE_JMP: begin
                isJMP    = 1'b1;
            end
        endcase
    end

endmodule



module RF(
    input [1:0] addr1,
    input [1:0] addr2,
    input [1:0] addr3,
    input [15:0] data3,
    input write,
    input clk,
    input reset,
    output reg [15:0] data1,
    output reg [15:0] data2
    );
    // FILLME
    
    
    reg [15:0] reg1,reg2,reg3,reg4;
    wire y1,y2,y3,y4;
    assign y1=((~addr3[0])&(~addr3[1]))&write;
    assign y2=((addr3[0])&(~addr3[1]))&write;
    assign y3=((~addr3[0])&(addr3[1]))&write;
    assign y4=((addr3[0])&(addr3[1]))&write;
    
    
    always@(posedge clk) begin
     if(reset) begin
        reg1 <= 0;
        reg2 <= 0;
        reg3 <= 0;
        reg4 <= 0;
    end
    else begin
        if(y1) reg1 <= data3;
        if(y2) reg2 <= data3;
        if(y3) reg3 <= data3;
        if(y4) reg4 <= data3;
    end
    end
    
    
    always@(reg1,reg2,reg3,reg4,addr1)begin
    if(!addr1[0]&!addr1[1]) data1= reg1;
    if(addr1[0]&!addr1[1])data1= reg2;
    if(!addr1[0]&addr1[1])data1= reg3;
    if(addr1[0]&addr1[1])data1= reg4;
    end
    
    always@(reg1,reg2,reg3,reg4,addr2)begin
    if(!addr2[0]&!addr2[1]) data2= reg1;
    if(addr2[0]&!addr2[1])data2= reg2;
    if(!addr2[0]&addr2[1])data2= reg3;
    if(addr2[0]&addr2[1])data2= reg4;
    end
    
endmodule



module ALU(
    input [15:0] A,
    input [15:0] B,
    input Cin,
    input [3:0] OP,
    output reg Cout,
    output reg [15:0] C
    );
    
    // FILLME
`define	OP_ADD	4'b0000
`define	OP_SUB	4'b0001
//  Bitwise Boolean operation
`define	OP_ID	4'b0010
`define	OP_NAND	4'b0011
`define	OP_NOR	4'b0100
`define	OP_XNOR	4'b0101
`define	OP_NOT	4'b0110
`define	OP_AND	4'b0111
`define	OP_OR	4'b1000
`define	OP_XOR	4'b1001
// Shifting
`define	OP_LRS	4'b1010
`define	OP_ARS	4'b1011
`define	OP_RR	4'b1100
`define	OP_LLS	4'b1101
`define	OP_ALS	4'b1110
`define	OP_RL	4'b1111
always @(*) begin
        Cout = 0;  // default
        C = 0;

        case (OP)
            // Arithmetic
            `OP_ADD: begin
                {Cout, C} = A + B + Cin;
            end

            `OP_SUB: begin
                {Cout, C} = A +(~B+1) - Cin;
            end

            // Bitwise
            `OP_ID:   C = A;
            `OP_NAND: C = ~(A & B);
            `OP_NOR:  C = ~(A | B);
            `OP_XNOR: C = ~(A ^ B);
            `OP_NOT:  C = ~A;
            `OP_AND:  C = A & B;
            `OP_OR:   C = A | B;
            `OP_XOR:  C = A ^ B;

            // Shifts
            `OP_LRS: begin
                C = A >> 1;
            end

            `OP_ARS: begin
                C = $signed(A) >>> 1;
            end

            `OP_LLS: begin
                C = A << 1;
            end

            `OP_ALS: begin
                C = A <<< 1; 
            end

            // Rotate
            `OP_RR: begin
                C = {A[0], A[15:1]};
            end

            `OP_RL: begin
                C = {A[14:0], A[15]};
            end

            default: begin
                C = 16'h0000;
            end
        endcase
    end
    
endmodule

cpu_tb.v
///////////////////////////////////////////////////////////////////////////
// MODULE: Test Bench for the TSC CPU module: tb_cpu.v
// Description: Tests the module "cpu.v"

// DEFINITIONS 
`timescale 1ns/100ps
`define PERIOD1 100
`define READ_DELAY 30   // delay before memory data is ready
`define WRITE_DELAY 30  // delay in writing to memory
`define STABLE_TIME 10  // time data is stable after end-of-read
`define MEMORY_SIZE 256 // size of memory is 2^8 words (reduced size)
`define WORD_SIZE 16    //   instead of 2^16 words to reduce memory
 //   requirements in the Active-HDL simulator

// MODULE DEFINITION
module tb_cpu();

  // SIGNAL DECLARATIONS for chip inputs and outputs
  wire readM;     // read from memory									
  wire [`WORD_SIZE-1:0] address; // current address for data input or output
  wire [`WORD_SIZE-1:0] data;    // data being input or output	  
  reg inputReady; // indicates that data is ready from the input port
  reg reset_n;    // active-low RESET signal
  reg clk;        // clock signal
  
  // for debuging purpose
  wire [`WORD_SIZE-1:0] num_inst;		// number of instruction during execution
  wire [`WORD_SIZE-1:0] output_port; // this will be used for a "WWD" instruction	  

  // SIGNAL DECLARATIONS for signals being used internally
  reg [`WORD_SIZE-1:0] outputData;  // data output during a memory read

  // instantiate the unit under test
  cpu UUT (readM, address, data, inputReady,
  			reset_n, clk, num_inst, output_port);
         

initial begin
    $dumpfile("cpu_test.vcd");   // vcd 파일 이름 지정
    $dumpvars(0, tb_cpu);        // 0 = 모든 하위 모듈 신호 다 덤프
end

         

  // initialize inputs
  initial begin
    clk = 0;           // set initial clock value
	inputReady = 0;

    reset_n = 1;       // generate a LOW pulse for reset_n
    #(`PERIOD1/4) reset_n = 0;
    #`PERIOD1 reset_n = 1;
  end

  // generate the clock
  always #(`PERIOD1/2)clk = ~clk;  // generates a clock (period = `PERIOD1)

  // model the memory device
  reg [`WORD_SIZE-1:0] memory [0:`MEMORY_SIZE-1];

  // model the read process for the memory device
  assign data = readM ? outputData : `WORD_SIZE'bz;
  always begin
    outputData = `WORD_SIZE'bz;
    #`PERIOD1;
    forever begin
      wait (readM == 1);
      #`READ_DELAY;
      outputData = memory[address];
	  inputReady = 1;
      #(`STABLE_TIME);
      outputData = `WORD_SIZE'bz;
	  inputReady = 0;
    end  // of forever loop
  end  // of always block for memory read
  
  // store programs and data in the memory
  initial begin
    #`PERIOD1;   // delay for a while
	memory[0]  = 16'h6000;	//	LHI $0, 0
	memory[1]  = 16'h6101;	//	LHI $1, 1
 	memory[2]  = 16'h6202;	//	LHI $2, 2
	memory[3]  = 16'h6303;	//	LHI $3, 3
	memory[4]  = 16'hf01c;	//	WWD $0
	memory[5]  = 16'hf41c;	//	WWD $1
	memory[6]  = 16'hf81c;	//	WWD $2
	memory[7]  = 16'hfc1c;	//	WWD $3
	memory[8]  = 16'h4204;	//	ADI $2, $0, 4
	memory[9]  = 16'h47fc;	//	ADI $3, $1, -4
	memory[10] = 16'hf81c;	//	WWD $2
	memory[11] = 16'hfc1c;	//	WWD $3
	memory[12] = 16'hf6c0;	//	ADD $3, $1, $2
	memory[13] = 16'hf180;	//	ADD $2, $0, $1
	memory[14] = 16'hf81c;	//	WWD $2
	memory[15] = 16'hfc1c;	//	WWD $3
	memory[16] = 16'h9015;	//	JMP 21
	memory[17] = 16'hf01c;	//	WWD $0
	memory[18] = 16'hf180;	//	ADD $2, $0, $1
	memory[19] = 16'hf180;	//	ADD $2, $0, $1
	memory[20] = 16'hf180;	//	ADD $2, $0, $1
	memory[21] = 16'h6000;	//	LHI $0, 0
	memory[22] = 16'h4000;	//	ADI $0, $0, 0
	memory[23] = 16'hfd80;	//	ADD $2, $3, $1
	memory[24] = 16'hf01c;	//	WWD $0
	memory[25] = 16'hf41c;	//	WWD $1
	memory[26] = 16'hf81c;	//	WWD $2
	memory[27] = 16'hfc1c;	//	WWD $3
	
	#(`PERIOD1*30);
   $finish();
  end
  
  // always process to check the results of the tests
  // ...

  always @(posedge clk) begin
     case (num_inst)
        16'd5: // for testing WWD $0
           if (output_port == 16'd0)
              $display ("PASS");
           else
              $display ("FAIL[%d/%d]",output_port, 16'd0);
        16'd6: // for testing WWD $1
           if (output_port == 16'd256)
              $display ("PASS");
           else
              $display ("FAIL[%d/%d]",output_port, 16'd256);
        16'd7: // for testing WWD $2
           if (output_port == 16'd512)
              $display ("PASS");
           else
              $display ("FAIL[%d/%d]",output_port, 16'd512);
        16'd8: // for testing WWD $3   
           if (output_port == 16'd768)
              $display ("PASS");
           else
              $display ("FAIL[%d/%d]",output_port, 16'd768);
        16'd11: // for testing WWD $2
           if (output_port == 16'd4)
              $display ("PASS");
           else
              $display ("FAIL[%d/%d]",output_port, 16'd4);
        16'd12: // for testing WWD $3
           if (output_port == 16'd252)
              $display ("PASS");
           else
              $display ("FAIL[%d/%d]",output_port, 16'd252);
        16'd15: // for testing WWD $2
           if (output_port == 16'd256)
              $display ("PASS");
           else
              $display ("FAIL[%d/%d]",output_port, 16'd256);
        16'd16: // for testing WWD $3
           if (output_port == 16'd260)
              $display ("PASS");
           else
              $display ("FAIL[%d/%d]",output_port, 16'd260);
        16'd21: // for testing WWD $0
           if (output_port == 16'd0)
              $display ("PASS");
           else
              $display ("FAIL[%d/%d]",output_port, 16'd0);
        16'd22: // for testing WWD $1
           if (output_port == 16'd256)
              $display ("PASS");
           else
              $display ("FAIL[%d/%d]",output_port, 16'd256);
        16'd23: // for testing WWD $2
           if (output_port == 16'd516)
              $display ("PASS");
           else
              $display ("FAIL[%d/%d]",output_port, 16'd516);
        16'd24: // for testing WWD $3
           if (output_port == 16'd260)
              $display ("PASS");
           else
              $display ("FAIL[%d/%d]",output_port, 16'd260);
     endcase
  end
endmodule
///////////////

cpu_test.vcd
$date
	Sun May 24 15:25:19 2026
$end
$version
	Icarus Verilog
$end
$timescale
	100ps
$end
$scope module tb_cpu $end
$var wire 1 ! readM $end
$var wire 16 " output_port [15:0] $end
$var wire 16 # num_inst [15:0] $end
$var wire 16 $ data [15:0] $end
$var wire 16 % address [15:0] $end
$var reg 1 & clk $end
$var reg 1 ' inputReady $end
$var reg 16 ( outputData [15:0] $end
$var reg 1 ) reset_n $end
$scope module UUT $end
$var wire 16 * address [15:0] $end
$var wire 1 & clk $end
$var wire 16 + data [15:0] $end
$var wire 1 ' inputReady $end
$var wire 16 , num_inst [15:0] $end
$var wire 16 - output_port [15:0] $end
$var wire 1 ! readM $end
$var wire 1 ) reset_n $end
$var wire 16 . write_data [15:0] $end
$var wire 2 / write_addr [1:0] $end
$var wire 12 0 target [11:0] $end
$var wire 16 1 sign_ext [15:0] $end
$var wire 2 2 rt [1:0] $end
$var wire 2 3 rs [1:0] $end
$var wire 16 4 reg_data2 [15:0] $end
$var wire 16 5 reg_data1 [15:0] $end
$var wire 2 6 rd [1:0] $end
$var wire 16 7 pc_out [15:0] $end
$var wire 16 8 lhi_val [15:0] $end
$var wire 1 9 isWWD $end
$var wire 1 : isLHI $end
$var wire 1 ; isJMP $end
$var wire 8 < imm [7:0] $end
$var wire 1 = alu_Cout $end
$var wire 16 > alu_C [15:0] $end
$var wire 16 ? alu_B [15:0] $end
$var wire 1 @ RegWrite $end
$var wire 1 A RegDst $end
$var wire 1 B ALUSrc $end
$var wire 3 C ALUOp [2:0] $end
$var reg 16 D instruction [15:0] $end
$var reg 16 E num_inst_r [15:0] $end
$var reg 16 F output_port_r [15:0] $end
$scope module CU $end
$var wire 16 G instruction [15:0] $end
$var wire 4 H opcode [3:0] $end
$var wire 6 I func [5:0] $end
$var reg 3 J ALUOp [2:0] $end
$var reg 1 B ALUSrc $end
$var reg 1 A RegDst $end
$var reg 1 @ RegWrite $end
$var reg 1 ; isJMP $end
$var reg 1 : isLHI $end
$var reg 1 9 isWWD $end
$upscope $end
$scope module alu $end
$var wire 16 K B [15:0] $end
$var wire 1 L Cin $end
$var wire 4 M OP [3:0] $end
$var wire 16 N A [15:0] $end
$var reg 16 O C [15:0] $end
$var reg 1 = Cout $end
$upscope $end
$scope module pc $end
$var wire 1 & clk $end
$var wire 1 ; isJMP $end
$var wire 12 P jump_target [11:0] $end
$var wire 1 ) reset_n $end
$var reg 16 Q pc_out [15:0] $end
$upscope $end
$scope module rf $end
$var wire 2 R addr1 [1:0] $end
$var wire 2 S addr2 [1:0] $end
$var wire 2 T addr3 [1:0] $end
$var wire 1 & clk $end
$var wire 16 U data3 [15:0] $end
$var wire 1 V reset $end
$var wire 1 @ write $end
$var wire 1 W y1 $end
$var wire 1 X y2 $end
$var wire 1 Y y3 $end
$var wire 1 Z y4 $end
$var reg 16 [ data1 [15:0] $end
$var reg 16 \ data2 [15:0] $end
$var reg 16 ] reg1 [15:0] $end
$var reg 16 ^ reg2 [15:0] $end
$var reg 16 _ reg3 [15:0] $end
$var reg 16 ` reg4 [15:0] $end
$upscope $end
$upscope $end
$upscope $end
$enddefinitions $end
$comment Show the parameter values. $end
$dumpall
$end
#0
$dumpvars
bx `
bx _
bx ^
bx ]
bx \
bx [
xZ
xY
xX
xW
0V
bx00000000 U
bx T
bx S
bx R
bx Q
bx P
b0 O
bx N
b0xxx M
0L
bx K
bx J
bx I
bx H
bx G
bx F
bx E
bx D
bx C
xB
xA
x@
bx ?
b0 >
0=
bx <
x;
x:
x9
bx00000000 8
bx 7
bx 6
bx 5
bx 4
bx 3
bx 2
bx 1
bx 0
bx /
bx00000000 .
bx -
bx ,
bz +
bx *
1)
bz (
0'
0&
bx %
bz $
bx #
bx "
1!
$end
#250
b0 %
b0 *
b0 7
b0 Q
b0 "
b0 -
b0 F
b0 #
b0 ,
b0 E
1V
0)
#500
b0 `
b0 _
b0 ^
b0 ]
1&
#1000
0&
#1250
0V
1)
#1300
1W
0X
0Y
0Z
b0 .
b0 U
b0 M
b0 ?
b0 K
b0 5
b0 N
b0 [
b0 4
b0 \
b0 /
b0 T
b0 1
b0 8
09
0;
1:
b0 C
b0 J
0B
0A
1@
b0 3
b0 R
b0 2
b0 S
b0 6
b0 <
b0 0
b0 P
b110 H
b0 I
b110000000000000 D
b110000000000000 G
1'
b110000000000000 $
b110000000000000 (
b110000000000000 +
#1400
0'
bz $
bz (
bz +
#1500
b1 %
b1 *
b1 7
b1 Q
b1 #
b1 ,
b1 E
1&
#1700
0W
1X
b100000000 .
b100000000 U
b1 /
b1 T
b1 1
b100000000 8
1:
1@
b1 2
b1 S
b1 <
b100000001 0
b100000001 P
b1 I
b110000100000001 D
b110000100000001 G
1'
b110000100000001 $
b110000100000001 (
b110000100000001 +
#1800
0'
bz $
bz (
bz +
#2000
0&
#2100
1'
b110000100000001 $
b110000100000001 (
b110000100000001 +
#2200
0'
bz $
bz (
bz +
#2500
b100000000 >
b100000000 O
b100000000 ?
b100000000 K
b100000000 4
b100000000 \
b10 #
b10 ,
b10 E
b10 %
b10 *
b10 7
b10 Q
b100000000 ^
1'
b110000100000001 $
b110000100000001 (
b110000100000001 +
1&
#2600
0'
bz $
bz (
bz +
#2900
1Y
0X
b0 >
b0 O
b0 ?
b0 K
b1000000000 .
b1000000000 U
b10 /
b10 T
b0 4
b0 \
b10 1
b1000000000 8
1:
1@
b10 2
b10 S
b10 <
b1000000010 0
b1000000010 P
b10 I
b110001000000010 D
b110001000000010 G
1'
b110001000000010 $
b110001000000010 (
b110001000000010 +
#3000
0'
bz $
bz (
bz +
0&
#3300
1'
b110001000000010 $
b110001000000010 (
b110001000000010 +
#3400
0'
bz $
bz (
bz +
#3500
b1000000000 >
b1000000000 O
b1000000000 ?
b1000000000 K
b1000000000 4
b1000000000 \
b11 %
b11 *
b11 7
b11 Q
b11 #
b11 ,
b11 E
b1000000000 _
1&
#3700
0Y
1Z
b0 >
b0 O
b0 ?
b0 K
b1100000000 .
b1100000000 U
b11 /
b11 T
b0 4
b0 \
b11 1
b1100000000 8
1:
1@
b11 2
b11 S
b11 <
b1100000011 0
b1100000011 P
b11 I
b110001100000011 D
b110001100000011 G
1'
b110001100000011 $
b110001100000011 (
b110001100000011 +
#3800
0'
bz $
bz (
bz +
#4000
0&
#4100
1'
b110001100000011 $
b110001100000011 (
b110001100000011 +
#4200
0'
bz $
bz (
bz +
#4500
b1100000000 >
b1100000000 O
b1100000000 ?
b1100000000 K
b1100000000 4
b1100000000 \
b100 #
b100 ,
b100 E
b100 %
b100 *
b100 7
b100 Q
b1100000000 `
1'
b110001100000011 $
b110001100000011 (
b110001100000011 +
1&
#4600
0'
bz $
bz (
bz +
#4900
b0 .
b0 U
b0 >
b0 O
b0 ?
b0 K
0Z
b0 /
b0 T
b0 4
b0 \
b11100 1
b1110000000000 8
19
0:
0@
b0 2
b0 S
b11100 <
b11100 0
b11100 P
b1111 H
b11100 I
b1111000000011100 D
b1111000000011100 G
1'
b1111000000011100 $
b1111000000011100 (
b1111000000011100 +
#5000
0'
bz $
bz (
bz +
0&
#5300
1'
b1111000000011100 $
b1111000000011100 (
b1111000000011100 +
#5400
0'
bz $
bz (
bz +
#5500
b101 %
b101 *
b101 7
b101 Q
b101 #
b101 ,
b101 E
1&
#5700
b100000000 .
b100000000 U
b100000000 >
b100000000 O
b100000000 5
b100000000 N
b100000000 [
b1 3
b1 R
b10000011100 0
b10000011100 P
b1111010000011100 D
b1111010000011100 G
1'
b1111010000011100 $
b1111010000011100 (
b1111010000011100 +
#5800
0'
bz $
bz (
bz +
#6000
0&
#6100
1'
b1111010000011100 $
b1111010000011100 (
b1111010000011100 +
#6200
0'
bz $
bz (
bz +
#6500
b100000000 "
b100000000 -
b100000000 F
b110 #
b110 ,
b110 E
b110 %
b110 *
b110 7
b110 Q
1'
b1111010000011100 $
b1111010000011100 (
b1111010000011100 +
1&
#6600
0'
bz $
bz (
bz +
#6900
b1000000000 .
b1000000000 U
b1000000000 >
b1000000000 O
b1000000000 5
b1000000000 N
b1000000000 [
b10 3
b10 R
b100000011100 0
b100000011100 P
b1111100000011100 D
b1111100000011100 G
1'
b1111100000011100 $
b1111100000011100 (
b1111100000011100 +
#7000
0'
bz $
bz (
bz +
0&
#7300
1'
b1111100000011100 $
b1111100000011100 (
b1111100000011100 +
#7400
0'
bz $
bz (
bz +
#7500
b111 %
b111 *
b111 7
b111 Q
b1000000000 "
b1000000000 -
b1000000000 F
b111 #
b111 ,
b111 E
1&
#7700
b1100000000 .
b1100000000 U
b1100000000 >
b1100000000 O
b1100000000 5
b1100000000 N
b1100000000 [
b11 3
b11 R
b110000011100 0
b110000011100 P
b1111110000011100 D
b1111110000011100 G
1'
b1111110000011100 $
b1111110000011100 (
b1111110000011100 +
#7800
0'
bz $
bz (
bz +
#8000
0&
#8100
1'
b1111110000011100 $
b1111110000011100 (
b1111110000011100 +
#8200
0'
bz $
bz (
bz +
#8500
b1100000000 "
b1100000000 -
b1100000000 F
b1000 #
b1000 ,
b1000 E
b1000 %
b1000 *
b1000 7
b1000 Q
1'
b1111110000011100 $
b1111110000011100 (
b1111110000011100 +
1&
#8600
0'
bz $
bz (
bz +
#8900
1Y
b100 .
b100 U
b100 >
b100 O
b100 ?
b100 K
0W
b0 5
b0 N
b0 [
b10 /
b10 T
b1000000000 4
b1000000000 \
b100 1
b10000000000 8
1B
1@
09
b0 3
b0 R
b10 2
b10 S
b100 <
b1000000100 0
b1000000100 P
b100 H
b100 I
b100001000000100 D
b100001000000100 G
1'
b100001000000100 $
b100001000000100 (
b100001000000100 +
#9000
0'
bz $
bz (
bz +
0&
#9300
1'
b100001000000100 $
b100001000000100 (
b100001000000100 +
#9400
0'
bz $
bz (
bz +
#9500
b100 4
b100 \
b1001 %
b1001 *
b1001 7
b1001 Q
b1001 #
b1001 ,
b1001 E
b100 _
1&
#9700
0Y
1Z
1=
b11111100 .
b11111100 U
b11111100 >
b11111100 O
b1111111111111100 ?
b1111111111111100 K
b100000000 5
b100000000 N
b100000000 [
b11 /
b11 T
b1100000000 4
b1100000000 \
b1111111111111100 1
b1111110000000000 8
1B
1@
b1 3
b1 R
b11 2
b11 S
b11 6
b11111100 <
b11111111100 0
b11111111100 P
b111100 I
b100011111111100 D
b100011111111100 G
1'
b100011111111100 $
b100011111111100 (
b100011111111100 +
#9800
0'
bz $
bz (
bz +
#10000
0&
#10100
1'
b100011111111100 $
b100011111111100 (
b100011111111100 +
#10200
0'
bz $
bz (
bz +
#10500
b11111100 4
b11111100 \
b1010 #
b1010 ,
b1010 E
b1010 %
b1010 *
b1010 7
b1010 Q
b11111100 `
1'
b100011111111100 $
b100011111111100 (
b100011111111100 +
1&
#10600
0'
bz $
bz (
bz +
#10900
b100 .
b100 U
b100 >
b100 O
0=
b0 ?
b0 K
0Z
b100 5
b100 N
b100 [
b0 /
b0 T
b0 4
b0 \
b11100 1
b1110000000000 8
19
0B
0@
b10 3
b10 R
b0 2
b0 S
b0 6
b11100 <
b100000011100 0
b100000011100 P
b1111 H
b11100 I
b1111100000011100 D
b1111100000011100 G
1'
b1111100000011100 $
b1111100000011100 (
b1111100000011100 +
#11000
0'
bz $
bz (
bz +
0&
#11300
1'
b1111100000011100 $
b1111100000011100 (
b1111100000011100 +
#11400
0'
bz $
bz (
bz +
#11500
b1011 %
b1011 *
b1011 7
b1011 Q
b100 "
b100 -
b100 F
b1011 #
b1011 ,
b1011 E
1&
#11700
b11111100 .
b11111100 U
b11111100 >
b11111100 O
b11111100 5
b11111100 N
b11111100 [
b11 3
b11 R
b110000011100 0
b110000011100 P
b1111110000011100 D
b1111110000011100 G
1'
b1111110000011100 $
b1111110000011100 (
b1111110000011100 +
#11800
0'
bz $
bz (
bz +
#12000
0&
#12100
1'
b1111110000011100 $
b1111110000011100 (
b1111110000011100 +
#12200
0'
bz $
bz (
bz +
#12500
b11111100 "
b11111100 -
b11111100 F
b1100 #
b1100 ,
b1100 E
b1100 %
b1100 *
b1100 7
b1100 Q
1'
b1111110000011100 $
b1111110000011100 (
b1111110000011100 +
1&
#12600
0'
bz $
bz (
bz +
#12900
0Y
1Z
b100000100 .
b100000100 U
b100000100 >
b100000100 O
b100 ?
b100 K
0W
b100000000 5
b100000000 N
b100000000 [
b11 /
b11 T
b100 4
b100 \
b1111111111000000 1
b1100000000000000 8
1A
1@
09
b1 3
b1 R
b10 2
b10 S
b11 6
b11000000 <
b11011000000 0
b11011000000 P
b0 I
b1111011011000000 D
b1111011011000000 G
1'
b1111011011000000 $
b1111011011000000 (
b1111011011000000 +
#13000
0'
bz $
bz (
bz +
0&
#13300
1'
b1111011011000000 $
b1111011011000000 (
b1111011011000000 +
#13400
0'
bz $
bz (
bz +
#13500
b1101 %
b1101 *
b1101 7
b1101 Q
b1101 #
b1101 ,
b1101 E
b100000100 `
1&
#13700
1Y
0Z
b100000000 .
b100000000 U
b100000000 >
b100000000 O
b100000000 ?
b100000000 K
b0 5
b0 N
b0 [
b100000000 4
b100000000 \
b10 /
b10 T
b1111111110000000 1
b1000000000000000 8
b0 3
b0 R
b1 2
b1 S
b10 6
b10000000 <
b110000000 0
b110000000 P
b1111000110000000 D
b1111000110000000 G
1'
b1111000110000000 $
b1111000110000000 (
b1111000110000000 +
#13800
0'
bz $
bz (
bz +
#14000
0&
#14100
1'
b1111000110000000 $
b1111000110000000 (
b1111000110000000 +
#14200
0'
bz $
bz (
bz +
#14500
b1110 #
b1110 ,
b1110 E
b1110 %
b1110 *
b1110 7
b1110 Q
b100000000 _
1'
b1111000110000000 $
b1111000110000000 (
b1111000110000000 +
1&
#14600
0'
bz $
bz (
bz +
#14900
b100000000 >
b100000000 O
b0 ?
b0 K
0Y
b100000000 5
b100000000 N
b100000000 [
b0 4
b0 \
b0 /
b0 T
b11100 1
b1110000000000 8
19
0A
0@
b10 3
b10 R
b0 2
b0 S
b0 6
b11100 <
b100000011100 0
b100000011100 P
b11100 I
b1111100000011100 D
b1111100000011100 G
1'
b1111100000011100 $
b1111100000011100 (
b1111100000011100 +
#15000
0'
bz $
bz (
bz +
0&
#15300
1'
b1111100000011100 $
b1111100000011100 (
b1111100000011100 +
#15400
0'
bz $
bz (
bz +
#15500
b1111 %
b1111 *
b1111 7
b1111 Q
b100000000 "
b100000000 -
b100000000 F
b1111 #
b1111 ,
b1111 E
1&
#15700
b100000100 .
b100000100 U
b100000100 >
b100000100 O
b100000100 5
b100000100 N
b100000100 [
b11 3
b11 R
b110000011100 0
b110000011100 P
b1111110000011100 D
b1111110000011100 G
1'
b1111110000011100 $
b1111110000011100 (
b1111110000011100 +
#15800
0'
bz $
bz (
bz +
#16000
0&
#16100
1'
b1111110000011100 $
b1111110000011100 (
b1111110000011100 +
#16200
0'
bz $
bz (
bz +
#16500
b100000100 "
b100000100 -
b100000100 F
b10000 #
b10000 ,
b10000 E
b10000 %
b10000 *
b10000 7
b10000 Q
1'
b1111110000011100 $
b1111110000011100 (
b1111110000011100 +
1&
#16600
0'
bz $
bz (
bz +
#16900
b0 .
b0 U
b0 >
b0 O
b0 5
b0 N
b0 [
b10101 1
b1010100000000 8
1;
09
b0 3
b0 R
b10101 <
b10101 0
b10101 P
b1001 H
b10101 I
b1001000000010101 D
b1001000000010101 G
1'
b1001000000010101 $
b1001000000010101 (
b1001000000010101 +
#17000
0'
bz $
bz (
bz +
0&
#17300
1'
b1001000000010101 $
b1001000000010101 (
b1001000000010101 +
#17400
0'
bz $
bz (
bz +
#17500
b10101 %
b10101 *
b10101 7
b10101 Q
b10001 #
b10001 ,
b10001 E
1&
#17700
1W
b0 1
b0 8
1:
1@
0;
b0 <
b0 0
b0 P
b110 H
b0 I
b110000000000000 D
b110000000000000 G
1'
b110000000000000 $
b110000000000000 (
b110000000000000 +
#17800
0'
bz $
bz (
bz +
#18000
0&
